{"cookies": [], "origins": [{"origin": "https://nikita-filonov.github.io", "localStorage": [{"name": "persist:users", "value": "{\"user\":\"{\\\"id\\\":\\\"e44be009-e795-4efe-a45f-9e10a75572e1\\\",\\\"email\\\":\\\"user.nam23232323232323232e@gmail.com\\\",\\\"username\\\":\\\"username\\\",\\\"password\\\":\\\"password\\\"}\",\"users\":\"[{\\\"id\\\":\\\"e44be009-e795-4efe-a45f-9e10a75572e1\\\",\\\"email\\\":\\\"user.nam23232323232323232e@gmail.com\\\",\\\"username\\\":\\\"username\\\",\\\"password\\\":\\\"password\\\"}]\",\"_persist\":\"{\\\"version\\\":-1,\\\"rehydrated\\\":true}\"}"}, {"name": "persist:courses", "value": "{\"course\":\"{\\\"id\\\":\\\"\\\",\\\"title\\\":\\\"\\\",\\\"userId\\\":\\\"\\\",\\\"maxScore\\\":0,\\\"minScore\\\":0,\\\"exercises\\\":[],\\\"description\\\":\\\"\\\",\\\"previewImage\\\":null,\\\"estimatedTime\\\":\\\"\\\"}\",\"courses\":\"[]\",\"_persist\":\"{\\\"version\\\":-1,\\\"rehydrated\\\":true}\"}"}]}]}